aasthaadvancepackage/__init__.py
aasthaadvancepackage-0.0.0.dist-info/METADATA
aasthaadvancepackage-0.0.0.dist-info/WHEEL
aasthaadvancepackage-0.0.0.dist-info/license.txt
aasthaadvancepackage-0.0.0.dist-info/top_level.txt
aasthaadvancepackage-0.0.0.dist-info/RECORD
